orange1_mcp_server_weaviate-0.1.0.dist-info/licenses/LICENSE
src/__init__.py
src/server.py
src/settings.py
src/weaviate.py
orange1_mcp_server_weaviate-0.1.0.dist-info/METADATA
orange1_mcp_server_weaviate-0.1.0.dist-info/WHEEL
orange1_mcp_server_weaviate-0.1.0.dist-info/top_level.txt
orange1_mcp_server_weaviate-0.1.0.dist-info/RECORD
