Metadata-Version: 2.4
Name: orange1-mcp-server-weaviate
Version: 0.1.0
Summary: Add your description here
Home-page: 
Author: orange1
Author-email: support@orange.ai
Requires-Python: >=3.6
License-File: LICENSE
Requires-Dist: weaviate-client==4.10.4
Dynamic: author
Dynamic: author-email
Dynamic: license-file
Dynamic: requires-python
